PAROS/__init__.py
PAROS/eyephantom.py
PAROS/fundscale.py
PAROS/data/__init__.py
PAROS/data/calibration/__init__.py
PAROS/data/calibration/Topcon/TRC_50DX.csv
PAROS/data/calibration/Topcon/TRC_50IX.csv
PAROS/data/lenses/__init__.py
PAROS/data/lenses/phantom.csv
paros-1.0.0.dist-info/METADATA
paros-1.0.0.dist-info/WHEEL
paros-1.0.0.dist-info/licenses/LICENSE
paros-1.0.0.dist-info/RECORD
