Metadata-Version: 2.1
Name: PAROS
Version: 1.0.0
Summary: PARaxial Optical fundus Scaling (PAROS)
Author-email: "Lennart J. Pors" <l.j.pors@lumc.nl>, "Jan-Willem M. Beenakker" <j.w.m.beenakker@lumc.nl>, Corné Haasjes <c.haasjes@lumc.nl>
License: MIT License
License-File: LICENSE
Keywords: ophthalmology,paraxial optics
Classifier: Development Status :: 5 - Production/Stable
Classifier: Programming Language :: Python :: 3
Classifier: Topic :: Scientific/Engineering :: Physics
Classifier: Typing :: Typed
Requires-Python: >=3.9
Requires-Dist: matplotlib
Requires-Dist: numpy
Requires-Dist: pandas
Requires-Dist: scipy
Requires-Dist: sympy
